sphinx_airflow_theme/__init__.py
sphinx_airflow_theme/breadcrumbs.html
sphinx_airflow_theme/footer.html
sphinx_airflow_theme/globaltoc.html
sphinx_airflow_theme/header.html
sphinx_airflow_theme/layout.html
sphinx_airflow_theme/searchbox.html
sphinx_airflow_theme/searchresults.html
sphinx_airflow_theme/suggest_change_button.html
sphinx_airflow_theme/theme.conf
sphinx_airflow_theme/version-selector.html
sphinx_airflow_theme/static/_gen/css/main-custom.min.css
sphinx_airflow_theme/static/_gen/css/main.min.css
sphinx_airflow_theme/static/_gen/js/docs.js
sphinx_airflow_theme/static/js/globaltoc.js
sphinx_airflow_theme-0.2.2.dist-info/METADATA
sphinx_airflow_theme-0.2.2.dist-info/WHEEL
sphinx_airflow_theme-0.2.2.dist-info/entry_points.txt
sphinx_airflow_theme-0.2.2.dist-info/top_level.txt
sphinx_airflow_theme-0.2.2.dist-info/RECORD
